{
    "東亞超級籃球聯賽": {
        "Index": [
            25
        ],
        "Summary": [
            "新竹街口攻城獅在東亞超級籃球聯賽冠軍賽中，以些微差距輸給琉球金塊。比賽過程中，攻城獅球員白浩明膝蓋受傷流血，曾多次被犯規。白浩明在簡單包紮後重返球場，拿下11分4籃板。儘管最後輸球，白浩明與教練卡米諾斯都肯定球隊表現，並表示將持續努力，從失敗中學習。"
        ],
        "Key": [
            "新竹街口攻城獅",
            "琉球金塊",
            "東亞超級籃球聯賽",
            "冠軍賽",
            "白浩明",
            "卡米諾斯"
        ],
        "Date": "2025-03-09",
        "URL": [
            "https://sports.ltn.com.tw/news/breakingnews/4974684"
        ]
    }
}