{
  "川普重塑俄烏戰爭格局": {
    "進展": [
      {
        "日期": "2025-02-25",
        "摘要": "川普贏得美國總統大選後，對俄政策出現轉變，尋求與俄羅斯和解，並公開批評烏克蘭總統澤連斯基。此舉造成歐洲盟友擔憂美國的承諾，普丁則視之為扭轉局勢的機會，可能重提先前被拒絕的關於歐洲勢力範圍和北約擴張的要求。然而，普丁也面臨戰爭的巨大損失和國內經濟壓力。川普的回歸改變了地緣政治格局，但戰爭走向仍充滿變數，最終結果取決於多方複雜的互動，以及美國國內對與俄羅斯和解的支持度。同時，親俄羅斯的信息在社群媒體上傳播，歐洲政局也面臨挑戰。",
        "關鍵字": ["俄烏戰爭", "川普", "普丁", "北約", "地緣政治", "談判", "歐洲", "美國"],
        "相關新聞索引": [1, 2, 3],
        "來源網址": ["https://cn.nytimes.com/world/20250225/putin-trump-russia-ukraine-war/zh-hant/", "https://today.line.me/tw/v2/article/eLYaBGD", "https://rg.ru/2025/02/25/novyj-kurs-trampa.html"]
      }
    ],
    "總結與分析": "川普的當選為俄烏戰爭帶來了新的變數，他的親俄立場和對北約的質疑，使普丁看到了結束戰爭並重塑歐洲勢力範圍的機會。然而，戰爭的巨大損耗、美國國內對俄羅斯的負面觀感，以及烏克蘭的抵抗意志，都將影響最終結果。此外，社群媒體上的信息戰和歐洲政局的不穩定性，也增加了局勢的複雜性。未來，川普與普丁的談判、歐洲盟友的反應、以及烏克蘭的抉擇，都將是決定戰爭走向的關鍵因素。這場戰爭的結局，不僅影響烏克蘭的命運，也將重塑全球地緣政治格局。"
  }
}