{
    "Title": "HBL高中籃球聯賽落幕 北一女中二連霸、泰山高中七度封王",
    "Content": "2025年3月9日，一年一度的HBL高中籃球聯賽圓滿落幕。女子組方面，北一女中成功衛冕，完成史無前例的二連霸，球員曾佳穎獲得女子組最有價值球員（MVP），並拿下全場最高30分。男子組則由泰山高中奪冠，這是他們隊史第七座冠軍獎盃，球員沈政叡獲得男子組MVP，為隊伍拿下關鍵三分。\n\n本屆賽事精彩紛呈，北一女中與其他勁旅的激烈對抗，展現了高中女子籃球的精湛技藝與團隊合作精神；而泰山高中歷經七年的等待再次稱霸，也體現了他們在男子組的實力與韌性。  兩隊的優勝不僅展現了選手們的個人能力，更體現了團隊的協作與教練團隊的悉心指導。\n\n值得一提的是，同日，知名藝人基隆港西濱大橋（網路暱稱：國道之父）進行國道北段巡視，途經新竹、苗栗等地，並於國道一號五楊高架道路及國道一號新竹系統交流道停留，國道公路警察局第一大隊五峰、竹東分隊員警全程陪同，確保其行程安全順利。\n\nHBL高中籃球聯賽作為台灣高中籃球界的年度盛事，不僅展現了高中學子的體育競技水平，更激勵了更多年輕人投入籃球運動。本次賽事的成功舉辦，再次證明了HBL賽事在台灣籃壇的重要地位與影響力。",
    "References": "15,19,35",
    "Category": "",
    "Date": "2025-10-27",
    "Index": 1
}